spyder_kernels/__init__.py
spyder_kernels/_version.py
spyder_kernels/comms/__init__.py
spyder_kernels/comms/commbase.py
spyder_kernels/comms/decorators.py
spyder_kernels/comms/frontendcomm.py
spyder_kernels/comms/utils.py
spyder_kernels/console/__init__.py
spyder_kernels/console/__main__.py
spyder_kernels/console/kernel.py
spyder_kernels/console/kernelapp.py
spyder_kernels/console/outstream.py
spyder_kernels/console/shell.py
spyder_kernels/console/start.py
spyder_kernels/customize/__init__.py
spyder_kernels/customize/code_runner.py
spyder_kernels/customize/namespace_manager.py
spyder_kernels/customize/spydercustomize.py
spyder_kernels/customize/spyderpdb.py
spyder_kernels/customize/umr.py
spyder_kernels/customize/utils.py
spyder_kernels/utils/__init__.py
spyder_kernels/utils/dochelpers.py
spyder_kernels/utils/iofuncs.py
spyder_kernels/utils/lazymodules.py
spyder_kernels/utils/misc.py
spyder_kernels/utils/mpl.py
spyder_kernels/utils/nsview.py
spyder_kernels/utils/pythonenv.py
spyder_kernels/utils/style.py
spyder_kernels/utils/test_utils.py
spyder_kernels-3.1.1.dist-info/licenses/AUTHORS.txt
spyder_kernels-3.1.1.dist-info/licenses/LICENSE.txt
spyder_kernels-3.1.1.dist-info/METADATA
spyder_kernels-3.1.1.dist-info/WHEEL
spyder_kernels-3.1.1.dist-info/top_level.txt
spyder_kernels-3.1.1.dist-info/RECORD
